{
    "NPWR00002_00": {
        "npCommunicationId": "NPWR00002_00",
        "trophyTitleName": "THE EYE OF JUDGMENT™ Trophies",
        "trophyTitleIconUrl": "https://image.api.playstation.com/trophy/np/NPWR00002_00_002EE610759F10A3D8BD38278BDE212CA49EA7F0B9/3AF62639404A7F716656FF3A975BC864EBA960C6.PNG",
        "trophyTitlePlatform": "PS3",
        "definedTrophies": {
            "platinum": 1,
            "gold": 1,
            "silver": 21,
            "bronze": 16
        },
        "service": "trophy"
    },
    "NPWR00032_00": {
        "npCommunicationId": "NPWR00032_00",
        "trophyTitleName": "Lemmings™",
        "trophyTitleIconUrl": "https://image.api.playstation.com/trophy/np/NPWR00032_00_00814360A811CD3720D54A5C3F74DF94FE89617311/7B7C540E1A5EA948FF81D128F436E9D0E0840EC3.PNG",
        "trophyTitlePlatform": "PS3",
        "definedTrophies": {
            "platinum": 0,
            "gold": 1,
            "silver": 3,
            "bronze": 8
        },
        "service": "trophy"
    },
    "NPWR00036_00": {
        "npCommunicationId": "NPWR00036_00",
        "trophyTitleName": "SingStar®",
        "trophyTitleIconUrl": "https://image.api.playstation.com/trophy/np/NPWR00036_00_0027BD98E76AFBBA260814D77CF73AED588E65F949/CEBE34904DAFC9D6AC9339A1B310E141B5BAB895.PNG",
        "trophyTitlePlatform": "PS3",
        "definedTrophies": {
            "platinum": 1,
            "gold": 7,
            "silver": 11,
            "bronze": 29
        },
        "service": "trophy"
    },
    "NPWR00044_00": {
        "npCommunicationId": "NPWR00044_00",
        "trophyTitleName": "Lemmings™",
        "trophyTitleIconUrl": "https://image.api.playstation.com/trophy/np/NPWR00044_00_00C3CDDAF14B115BBB24A44BD26E2B191A658D0785/0B9772B3FC5FEC2FBE6006AE5D39B0EB31E0F60B.PNG",
        "trophyTitlePlatform": "PS3",
        "definedTrophies": {
            "platinum": 0,
            "gold": 1,
            "silver": 3,
            "bronze": 8
        },
        "service": "trophy"
    },
    "NPWR00049_00": {
        "npCommunicationId": "NPWR00049_00",
        "trophyTitleName": "Lemmings™",
        "trophyTitleIconUrl": "https://image.api.playstation.com/trophy/np/NPWR00049_00_003F3B893563D0760B778F3DD5DA800DB8649EED17/42D7C8AD5960AB596C8B9A7498D346AA6A669721.PNG",
        "trophyTitlePlatform": "PS3",
        "definedTrophies": {
            "platinum": 0,
            "gold": 1,
            "silver": 3,
            "bronze": 8
        },
        "service": "trophy"
    },
    "NPWR00050_00": {
        "npCommunicationId": "NPWR00050_00",
        "trophyTitleName": "PlayStation®Home",
        "trophyTitleIconUrl": "https://image.api.playstation.com/trophy/np/NPWR00050_00_00F640216909F8C8C95B79AECEB84B54D4B2F05064/34573B2BAC22E236A60C6FEE61EE51EE4F49C1EE.PNG",
        "trophyTitlePlatform": "PS3",
        "definedTrophies": {
            "platinum": 0,
            "gold": 1,
            "silver": 3,
            "bronze": 9
        },
        "service": "trophy"
    },
    "NPWR00051_00": {
        "npCommunicationId": "NPWR00051_00",
        "trophyTitleName": "まいにちいっしょ",
        "trophyTitleIconUrl": "https://image.api.playstation.com/trophy/np/NPWR00051_00_000296CA2215F2F67EFCD4A585B12B42D3C0DD1154/610E49D3C6310300E8FD211CBF77F814246F173C.PNG",
        "trophyTitlePlatform": "PS3",
        "definedTrophies": {
            "platinum": 0,
            "gold": 2,
            "silver": 2,
            "bronze": 3
        },
        "service": "trophy"
    },
    "NPWR00054_00": {
        "npCommunicationId": "NPWR00054_00",
        "trophyTitleName": "Blast Factor™ Trophies",
        "trophyTitleIconUrl": "https://image.api.playstation.com/trophy/np/NPWR00054_00_0033B6FBAB7E85DC8FA7C81C4521501CBAD0F098CF/A22765414DB585EB14EA1837CB2B09FBAADBC972.PNG",
        "trophyTitlePlatform": "PS3",
        "definedTrophies": {
            "platinum": 0,
            "gold": 0,
            "silver": 11,
            "bronze": 14
        },
        "service": "trophy"
    },
    "NPWR00071_00": {
        "npCommunicationId": "NPWR00071_00",
        "trophyTitleName": "flOw trophy set",
        "trophyTitleIconUrl": "https://image.api.playstation.com/trophy/np/NPWR00071_00_00DA34B9187CAEB021769C92798AB5ACAF11C8E64C/233283F1AE8525F13A8DA7A79D89CE72F4EB5C76.PNG",
        "trophyTitlePlatform": "PS3",
        "definedTrophies": {
            "platinum": 0,
            "gold": 1,
            "silver": 3,
            "bronze": 10
        },
        "service": "trophy"
    },
    "NPWR00088_00": {
        "npCommunicationId": "NPWR00088_00",
        "trophyTitleName": "High Stakes on the Vegas Strip: Poker Edition",
        "trophyTitleIconUrl": "https://image.api.playstation.com/trophy/np/NPWR00088_00_00C070B5A3A5E708E2A3EBEC5C799E5DC51428D326/4FFFF5A4BB3A25F8D1BFB3437EAC5F6B8F630687.PNG",
        "trophyTitlePlatform": "PS3",
        "definedTrophies": {
            "platinum": 0,
            "gold": 1,
            "silver": 5,
            "bronze": 8
        },
        "service": "trophy"
    },
    "NPWR00106_00": {
        "npCommunicationId": "NPWR00106_00",
        "trophyTitleName": "Wheel of Fortune",
        "trophyTitleIconUrl": "https://image.api.playstation.com/trophy/np/NPWR00106_00_00CDA74886DC70D9D64B598C55C18BA6B531713295/5F8EFD629941FD183AABEF2E48057424E4898C52.PNG",
        "trophyTitlePlatform": "PS3",
        "definedTrophies": {
            "platinum": 0,
            "gold": 1,
            "silver": 3,
            "bronze": 9
        },
        "service": "trophy"
    },
    "NPWR00116_00": {
        "npCommunicationId": "NPWR00116_00",
        "trophyTitleName": "NOBY NOBY BOY™",
        "trophyTitleIconUrl": "https://image.api.playstation.com/trophy/np/NPWR00116_00_00619D1F53E68239F8B32895087C865E8C4AB5B454/C39573646DA9E9E8892C9A32E9C43A11F8845E76.PNG",
        "trophyTitlePlatform": "PS3",
        "definedTrophies": {
            "platinum": 0,
            "gold": 1,
            "silver": 4,
            "bronze": 7
        },
        "service": "trophy"
    },
    "NPWR00117_00": {
        "npCommunicationId": "NPWR00117_00",
        "trophyTitleName": "SUPER STARDUST™ HD",
        "trophyTitleIconUrl": "https://image.api.playstation.com/trophy/np/NPWR00117_00_00E2D6C0A2BB7475BC6C26626F04790CDAD0507E33/797A9F853E90AE722EE315B9A8747E0842390FF3.PNG",
        "trophyTitlePlatform": "PS3",
        "definedTrophies": {
            "platinum": 0,
            "gold": 2,
            "silver": 6,
            "bronze": 9
        },
        "service": "trophy"
    },
    "NPWR00129_00": {
        "npCommunicationId": "NPWR00129_00",
        "trophyTitleName": "High Velocity Bowling™",
        "trophyTitleIconUrl": "https://image.api.playstation.com/trophy/np/NPWR00129_00_006149C528618383B438B2C139E76824BA9AFEE79F/782AFE7228E8963D23B18F8A2D72A4DC6B01F185.PNG",
        "trophyTitlePlatform": "PS3",
        "definedTrophies": {
            "platinum": 0,
            "gold": 1,
            "silver": 4,
            "bronze": 7
        },
        "service": "trophy"
    },
    "NPWR00132_00": {
        "npCommunicationId": "NPWR00132_00",
        "trophyTitleName": "GTA IV",
        "trophyTitleIconUrl": "https://image.api.playstation.com/trophy/np/NPWR00132_00_00418E3A341F6601FE2B592B96542E57D66D440367/5A7D06DD11D58892AFD1A5681FEEAB33F5C050A6.PNG",
        "trophyTitlePlatform": "PS3",
        "definedTrophies": {
            "platinum": 1,
            "gold": 3,
            "silver": 5,
            "bronze": 57
        },
        "service": "trophy"
    },
    "NPWR00133_00": {
        "npCommunicationId": "NPWR00133_00",
        "trophyTitleName": "Just Cause 2",
        "trophyTitleIconUrl": "https://image.api.playstation.com/trophy/np/NPWR00133_00_00EFFA6E8AA7EE7394DC1ED64614E5855D5E0A875F/CF2EF2120D31C2EC96FB599CBEF3BBE97133DCCD.PNG",
        "trophyTitlePlatform": "PS3",
        "definedTrophies": {
            "platinum": 1,
            "gold": 3,
            "silver": 5,
            "bronze": 42
        },
        "service": "trophy"
    },
    "NPWR00134_00": {
        "npCommunicationId": "NPWR00134_00",
        "trophyTitleName": "MOBILE SUIT GUNDAM BATTLEFIELD RECORD U.C.0081",
        "trophyTitleIconUrl": "https://image.api.playstation.com/trophy/np/NPWR00134_00_0050DEF69EB30C3832A7317B2ADED87E47550FFC14/A0BEAEAAA1B7B75B306DE4B854AB7725C28395CA.PNG",
        "trophyTitlePlatform": "PS3",
        "definedTrophies": {
            "platinum": 1,
            "gold": 4,
            "silver": 12,
            "bronze": 22
        },
        "service": "trophy"
    },
    "NPWR00153_00": {
        "npCommunicationId": "NPWR00153_00",
        "trophyTitleName": "Killzone 2",
        "trophyTitleIconUrl": "https://image.api.playstation.com/trophy/np/NPWR00153_00_00415AC3B975E7285378E228D05C1FA13F9A1AE2B2/EA108414E92E1C3E62FD8F9BA13F790AB0B28800.PNG",
        "trophyTitlePlatform": "PS3",
        "definedTrophies": {
            "platinum": 1,
            "gold": 3,
            "silver": 8,
            "bronze": 72
        },
        "service": "trophy"
    },
    "NPWR00156_00": {
        "npCommunicationId": "NPWR00156_00",
        "trophyTitleName": "Star Wars: The Force Unleashed",
        "trophyTitleIconUrl": "https://image.api.playstation.com/trophy/np/NPWR00156_00_006E63068D87B26BC542BD703E41070CF8B0C09686/09D5E05C6E22B6905ACB8E421B66399186FD68AB.PNG",
        "trophyTitlePlatform": "PS3",
        "definedTrophies": {
            "platinum": 1,
            "gold": 5,
            "silver": 16,
            "bronze": 43
        },
        "service": "trophy"
    },
    "NPWR00160_00": {
        "npCommunicationId": "NPWR00160_00",
        "trophyTitleName": "LittleBigPlanet™",
        "trophyTitleIconUrl": "https://image.api.playstation.com/trophy/np/NPWR00160_00_008E284646AFE80C3D45BBA5D6763ADDF683823CD4/618335118495DB7BB706D3477EB7C4F86D0629A6.PNG",
        "trophyTitlePlatform": "PS3",
        "definedTrophies": {
            "platinum": 1,
            "gold": 3,
            "silver": 12,
            "bronze": 54
        },
        "service": "trophy"
    },
    "NPWR00163_00": {
        "npCommunicationId": "NPWR00163_00",
        "trophyTitleName": "Warhawk",
        "trophyTitleIconUrl": "https://image.api.playstation.com/trophy/np/NPWR00163_00_006A0132F2CD3E1F3814C36072E4B2494F04353413/D4AEC63DADD0F010298C77C2683E79589EAD7352.PNG",
        "trophyTitlePlatform": "PS3",
        "definedTrophies": {
            "platinum": 1,
            "gold": 7,
            "silver": 13,
            "bronze": 36
        },
        "service": "trophy"
    },
    "NPWR00179_00": {
        "npCommunicationId": "NPWR00179_00",
        "trophyTitleName": "Pure Trophies",
        "trophyTitleIconUrl": "https://image.api.playstation.com/trophy/np/NPWR00179_00_00DD60793B8BA4A5CE171F444C73399863EE2594CA/62A2777C0835F8951A118854E6F99AF1C4FEF814.PNG",
        "trophyTitlePlatform": "PS3",
        "definedTrophies": {
            "platinum": 1,
            "gold": 3,
            "silver": 14,
            "bronze": 24
        },
        "service": "trophy"
    },
    "NPWR00180_00": {
        "npCommunicationId": "NPWR00180_00",
        "trophyTitleName": "Midnight Club: Los Angeles",
        "trophyTitleIconUrl": "https://image.api.playstation.com/trophy/np/NPWR00180_00_0037E9445D6FBDCA4BC047ECD3C58A9B5A1971D363/480FCBDB4697212C2C76BE48C00C56ABB3143DFF.PNG",
        "trophyTitlePlatform": "PS3",
        "definedTrophies": {
            "platinum": 1,
            "gold": 1,
            "silver": 21,
            "bronze": 33
        },
        "service": "trophy"
    },
    "NPWR00181_00": {
        "npCommunicationId": "NPWR00181_00",
        "trophyTitleName": "echochrome™",
        "trophyTitleIconUrl": "https://image.api.playstation.com/trophy/np/NPWR00181_00_00EBFE68D629BF7D7EED86E30E5DE77C3B66D086FC/C327903B6DEC0DB2D2F38DD735783BA930E6C872.PNG",
        "trophyTitlePlatform": "PS3",
        "definedTrophies": {
            "platinum": 0,
            "gold": 2,
            "silver": 1,
            "bronze": 7
        },
        "service": "trophy"
    },
    "NPWR00187_00": {
        "npCommunicationId": "NPWR00187_00",
        "trophyTitleName": "WipEout® HD Trophies",
        "trophyTitleIconUrl": "https://image.api.playstation.com/trophy/np/NPWR00187_00_00311F26296C49C4A9D544E75F435C6CE4972E8C1F/0715F96A747099B20A29B393B67CB06CA9368F1F.PNG",
        "trophyTitlePlatform": "PS3",
        "definedTrophies": {
            "platinum": 1,
            "gold": 5,
            "silver": 7,
            "bronze": 38
        },
        "service": "trophy"
    },
    "NPWR00194_00": {
        "npCommunicationId": "NPWR00194_00",
        "trophyTitleName": "Unreal Tournament ® 3",
        "trophyTitleIconUrl": "https://image.api.playstation.com/trophy/np/NPWR00194_00_003095A6CA09630F32E1947B6985E7A01EFD7161DA/F33189BDA343083A6B4454B579DB9CABCA40F550.PNG",
        "trophyTitlePlatform": "PS3",
        "definedTrophies": {
            "platinum": 1,
            "gold": 3,
            "silver": 8,
            "bronze": 36
        },
        "service": "trophy"
    },
    "NPWR00196_00": {
        "npCommunicationId": "NPWR00196_00",
        "trophyTitleName": "PAIN",
        "trophyTitleIconUrl": "https://image.api.playstation.com/trophy/np/NPWR00196_00_00C8F97276BE47F31C685D82160C235AC301A85C6E/7F3687EECE66832BF802708BA4E90C3B7B8137B4.PNG",
        "trophyTitlePlatform": "PS3",
        "definedTrophies": {
            "platinum": 0,
            "gold": 6,
            "silver": 12,
            "bronze": 23
        },
        "service": "trophy"
    },
    "NPWR00206_00": {
        "npCommunicationId": "NPWR00206_00",
        "trophyTitleName": "The Chronicles of Riddick™ Assault on Dark Athena",
        "trophyTitleIconUrl": "https://image.api.playstation.com/trophy/np/NPWR00206_00_0077677D7010EBBAE9686A8372BDCF78D146979D24/C7A572846E05CDDA630829A585B00C68B1D2A12C.PNG",
        "trophyTitlePlatform": "PS3",
        "definedTrophies": {
            "platinum": 1,
            "gold": 3,
            "silver": 5,
            "bronze": 42
        },
        "service": "trophy"
    },
    "NPWR00212_00": {
        "npCommunicationId": "NPWR00212_00",
        "trophyTitleName": "Ferrari Challenge",
        "trophyTitleIconUrl": "https://image.api.playstation.com/trophy/np/NPWR00212_00_001619D6A2CE2548540328A6AA7C285BAF53085CDA/53A418183D0F32D7CC11AA13D047306F198F9091.PNG",
        "trophyTitlePlatform": "PS3",
        "definedTrophies": {
            "platinum": 1,
            "gold": 4,
            "silver": 5,
            "bronze": 36
        },
        "service": "trophy"
    },
    "NPWR00214_00": {
        "npCommunicationId": "NPWR00214_00",
        "trophyTitleName": "MotorStorm®: Pacific Rift",
        "trophyTitleIconUrl": "https://image.api.playstation.com/trophy/np/NPWR00214_00_007FD7DEEDACBA61EF5DB5F9B5ADFF06C1278CD01A/214A6065C703972256800FE4745F749C230023C9.PNG",
        "trophyTitlePlatform": "PS3",
        "definedTrophies": {
            "platinum": 1,
            "gold": 4,
            "silver": 11,
            "bronze": 50
        },
        "service": "trophy"
    },
    "NPWR00234_00": {
        "npCommunicationId": "NPWR00234_00",
        "trophyTitleName": "Burnout™ Paradise",
        "trophyTitleIconUrl": "https://image.api.playstation.com/trophy/np/NPWR00234_00_00D1EE47DC19BE5210C9A03E4C12D0416CE654D413/D8303B0EBB2CB613D48A023DFF1C77390D654A30.PNG",
        "trophyTitlePlatform": "PS3",
        "definedTrophies": {
            "platinum": 1,
            "gold": 4,
            "silver": 28,
            "bronze": 65
        },
        "service": "trophy"
    },
    "NPWR00245_00": {
        "npCommunicationId": "NPWR00245_00",
        "trophyTitleName": "Demon's Souls",
        "trophyTitleIconUrl": "https://image.api.playstation.com/trophy/np/NPWR00245_00_0033A3A71C90F843F8132746DA6796F18EDD348170/A2F00D6AB19DFDA5C2ACD746C2EADC69C2350183.PNG",
        "trophyTitlePlatform": "PS3",
        "definedTrophies": {
            "platinum": 1,
            "gold": 5,
            "silver": 5,
            "bronze": 27
        },
        "service": "trophy"
    },
    "NPWR00251_00": {
        "npCommunicationId": "NPWR00251_00",
        "trophyTitleName": "WET",
        "trophyTitleIconUrl": "https://image.api.playstation.com/trophy/np/NPWR00251_00_00E4E36230A55FF3B04401FEBA8AB03A69D892DB6B/EF00692871C3110EB61ACDD438812A96E56F8428.PNG",
        "trophyTitlePlatform": "PS3",
        "definedTrophies": {
            "platinum": 1,
            "gold": 4,
            "silver": 10,
            "bronze": 26
        },
        "service": "trophy"
    },
    "NPWR00254_00": {
        "npCommunicationId": "NPWR00254_00",
        "trophyTitleName": "Red Faction: Guerrilla",
        "trophyTitleIconUrl": "https://image.api.playstation.com/trophy/np/NPWR00254_00_002BB220E10B9F156F89015980110835F086DAE68B/CEA1700BAD74581BD19504FE4CCA13CD0F47B114.PNG",
        "trophyTitlePlatform": "PS3",
        "definedTrophies": {
            "platinum": 1,
            "gold": 3,
            "silver": 8,
            "bronze": 49
        },
        "service": "trophy"
    },
    "NPWR00257_00": {
        "npCommunicationId": "NPWR00257_00",
        "trophyTitleName": "PixelJunk™ Monsters and Encore",
        "trophyTitleIconUrl": "https://image.api.playstation.com/trophy/np/NPWR00257_00_003B9303D4FA488B75E6ECDB1F877524880832071D/F39F0333F4EA8595C6090230A226590768628261.PNG",
        "trophyTitlePlatform": "PS3",
        "definedTrophies": {
            "platinum": 0,
            "gold": 1,
            "silver": 3,
            "bronze": 15
        },
        "service": "trophy"
    },
    "NPWR00261_00": {
        "npCommunicationId": "NPWR00261_00",
        "trophyTitleName": "[PROTOTYPE]™",
        "trophyTitleIconUrl": "https://image.api.playstation.com/trophy/np/NPWR00261_00_008BE8912C7BE7A727B24674FF1D87B1219449D5B8/A30CE14EE652E0C0BF7433E4C0F096EE13CB6B8D.PNG",
        "trophyTitlePlatform": "PS3",
        "definedTrophies": {
            "platinum": 1,
            "gold": 4,
            "silver": 10,
            "bronze": 26
        },
        "service": "trophy"
    },
    "NPWR00273_00": {
        "npCommunicationId": "NPWR00273_00",
        "trophyTitleName": "BattleFantasia",
        "trophyTitleIconUrl": "https://image.api.playstation.com/trophy/np/NPWR00273_00_00C5A2630BE8241CBBDBEF538C01002F0300AAB7BB/6886AADAFAB7EC062D3DF445C3CAF96548EBE6FB.PNG",
        "trophyTitlePlatform": "PS3",
        "definedTrophies": {
            "platinum": 1,
            "gold": 1,
            "silver": 4,
            "bronze": 56
        },
        "service": "trophy"
    },
    "NPWR00280_00": {
        "npCommunicationId": "NPWR00280_00",
        "trophyTitleName": "The Last Guy",
        "trophyTitleIconUrl": "https://image.api.playstation.com/trophy/np/NPWR00280_00_006B70ECD3F6E935403560869FB60929721883492C/6292A4AA19FEED4EAD392075510ED53ABE8E8B88.PNG",
        "trophyTitlePlatform": "PS3",
        "definedTrophies": {
            "platinum": 0,
            "gold": 2,
            "silver": 1,
            "bronze": 20
        },
        "service": "trophy"
    },
    "NPWR00283_00": {
        "npCommunicationId": "NPWR00283_00",
        "trophyTitleName": "Bionic Commando Rearmed",
        "trophyTitleIconUrl": "https://image.api.playstation.com/trophy/np/NPWR00283_00_005E7861476C9C55D53E3F6D188FC7BDBA87308472/7208A5D38C624DF1E01F77FA4084501DACB87121.PNG",
        "trophyTitlePlatform": "PS3",
        "definedTrophies": {
            "platinum": 0,
            "gold": 1,
            "silver": 4,
            "bronze": 7
        },
        "service": "trophy"
    },
    "NPWR00284_00": {
        "npCommunicationId": "NPWR00284_00",
        "trophyTitleName": "GTI Club + Rally Cote D'Azur",
        "trophyTitleIconUrl": "https://image.api.playstation.com/trophy/np/NPWR00284_00_0098BC2B441A1817C6715DF723A815B0EF35F292CE/8A822C5E084F302BE712D0056DA549E099215D63.PNG",
        "trophyTitlePlatform": "PS3",
        "definedTrophies": {
            "platinum": 0,
            "gold": 1,
            "silver": 6,
            "bronze": 15
        },
        "service": "trophy"
    },
    "NPWR00287_00": {
        "npCommunicationId": "NPWR00287_00",
        "trophyTitleName": "Ferrari Racing Legends",
        "trophyTitleIconUrl": "https://image.api.playstation.com/trophy/np/NPWR00287_00_00A5EA67998831AE55877D409F9BA3698D5BF6A0B3/4A88D07CC5626A61F4DBC3BE9A43A44ADD2082B7.PNG",
        "trophyTitlePlatform": "PS3",
        "definedTrophies": {
            "platinum": 1,
            "gold": 4,
            "silver": 5,
            "bronze": 36
        },
        "service": "trophy"
    },
    "NPWR00288_00": {
        "npCommunicationId": "NPWR00288_00",
        "trophyTitleName": "Damnation™",
        "trophyTitleIconUrl": "https://image.api.playstation.com/trophy/np/NPWR00288_00_004194164D5CC216C30FE6C46148E2B7876A64B001/4C26719EC65C849B7567F65C7176ACDBA21A7A29.PNG",
        "trophyTitlePlatform": "PS3",
        "definedTrophies": {
            "platinum": 1,
            "gold": 7,
            "silver": 7,
            "bronze": 14
        },
        "service": "trophy"
    },
    "NPWR00291_00": {
        "npCommunicationId": "NPWR00291_00",
        "trophyTitleName": "Resistance 2™",
        "trophyTitleIconUrl": "https://image.api.playstation.com/trophy/np/NPWR00291_00_00F20E479E0C56CFD77D2B5588B25B0DD71FBB1B1B/8F0B2E25C3524F1EF9EE87AD1999F7FD8A5EC4F8.PNG",
        "trophyTitlePlatform": "PS3",
        "definedTrophies": {
            "platinum": 1,
            "gold": 4,
            "silver": 8,
            "bronze": 26
        },
        "service": "trophy"
    },
    "NPWR00295_00": {
        "npCommunicationId": "NPWR00295_00",
        "trophyTitleName": "Twisted Metal™",
        "trophyTitleIconUrl": "https://image.api.playstation.com/trophy/np/NPWR00295_00_004A7414C3175D3BFECABEBF7EA08216711D7FAA09/B8AA498D59F04DBFB5907D68DA27BFDAAD95B66F.PNG",
        "trophyTitlePlatform": "PS3",
        "definedTrophies": {
            "platinum": 1,
            "gold": 5,
            "silver": 5,
            "bronze": 29
        },
        "service": "trophy"
    },
    "NPWR00300_00": {
        "npCommunicationId": "NPWR00300_00",
        "trophyTitleName": "ModNation™ Racers",
        "trophyTitleIconUrl": "https://image.api.playstation.com/trophy/np/NPWR00300_00_008B520AEA86D68CD1876D7CD068375F8F97BC5F52/95312EA347C857E4C8221C963A035D9EAF8DE728.PNG",
        "trophyTitlePlatform": "PS3",
        "definedTrophies": {
            "platinum": 1,
            "gold": 6,
            "silver": 11,
            "bronze": 51
        },
        "service": "trophy"
    },
    "NPWR00302_00": {
        "npCommunicationId": "NPWR00302_00",
        "trophyTitleName": "SOCOM: U.S. NAVY SEALS CONFRONTATION",
        "trophyTitleIconUrl": "https://image.api.playstation.com/trophy/np/NPWR00302_00_00DC4FDF3B64A5C34131263976CC8FE8E2C542F82D/9052EF174E4F43CB087B593AAB5E0A8DC4E3545F.PNG",
        "trophyTitlePlatform": "PS3",
        "definedTrophies": {
            "platinum": 1,
            "gold": 3,
            "silver": 23,
            "bronze": 16
        },
        "service": "trophy"
    },
    "NPWR00305_00": {
        "npCommunicationId": "NPWR00305_00",
        "trophyTitleName": "Bionic Commando",
        "trophyTitleIconUrl": "https://image.api.playstation.com/trophy/np/NPWR00305_00_00D1A80104E622EEB6665CBDE89403F71A7651288F/E7497A36512726EE85EECB5388781CCEBBCB4ED0.PNG",
        "trophyTitlePlatform": "PS3",
        "definedTrophies": {
            "platinum": 1,
            "gold": 3,
            "silver": 4,
            "bronze": 42
        },
        "service": "trophy"
    },
    "NPWR00306_00": {
        "npCommunicationId": "NPWR00306_00",
        "trophyTitleName": "Punisher: No Mercy",
        "trophyTitleIconUrl": "https://image.api.playstation.com/trophy/np/NPWR00306_00_00DA3ECD2528BAEB3DFE2863BC951747C167CABB55/9EF14B208939B1111F0A8E00FA4C1329D67EA875.PNG",
        "trophyTitlePlatform": "PS3",
        "definedTrophies": {
            "platinum": 0,
            "gold": 1,
            "silver": 4,
            "bronze": 7
        },
        "service": "trophy"
    },
    "NPWR00312_00": {
        "npCommunicationId": "NPWR00312_00",
        "trophyTitleName": "ACE COMBAT ASSAULT HORIZON",
        "trophyTitleIconUrl": "https://image.api.playstation.com/trophy/np/NPWR00312_00_0053F0092982AC4DA797E0B27964DF64D9F8D6709A/A6D52892DBB8CD22A94F61B648FA3DF503741014.PNG",
        "trophyTitlePlatform": "PS3",
        "definedTrophies": {
            "platinum": 1,
            "gold": 2,
            "silver": 10,
            "bronze": 38
        },
        "service": "trophy"
    },
    "NPWR00313_00": {
        "npCommunicationId": "NPWR00313_00",
        "trophyTitleName": "Geon",
        "trophyTitleIconUrl": "https://image.api.playstation.com/trophy/np/NPWR00313_00_005064244DF69EE0237D83D62A2E14C75AD63B33CC/260AD22DCA53B7C11E12E6B15367183EA008F6D9.PNG",
        "trophyTitlePlatform": "PS3",
        "definedTrophies": {
            "platinum": 0,
            "gold": 1,
            "silver": 4,
            "bronze": 7
        },
        "service": "trophy"
    },
    "NPWR00314_00": {
        "npCommunicationId": "NPWR00314_00",
        "trophyTitleName": "白騎士物語®－古の鼓動－トロフィーセット",
        "trophyTitleIconUrl": "https://image.api.playstation.com/trophy/np/NPWR00314_00_005006D62C49B493CA357480DC30C8CC85D7D0D1AE/BB2B9925AA81330F5E44783090C0011BA10C328A.PNG",
        "trophyTitlePlatform": "PS3",
        "definedTrophies": {
            "platinum": 1,
            "gold": 8,
            "silver": 7,
            "bronze": 8
        },
        "service": "trophy"
    },
    "NPWR00319_00": {
        "npCommunicationId": "NPWR00319_00",
        "trophyTitleName": "Tom Clancy’s H.A.W.X",
        "trophyTitleIconUrl": "https://image.api.playstation.com/trophy/np/NPWR00319_00_002B3D925761E533558DFFF97F6A8C3F3DE9ED69F8/0FBEB1A85C65EA83C9BB4CBDFABD5E94A904D0D0.PNG",
        "trophyTitlePlatform": "PS3",
        "definedTrophies": {
            "platinum": 1,
            "gold": 2,
            "silver": 8,
            "bronze": 40
        },
        "service": "trophy"
    },
    "NPWR00323_00": {
        "npCommunicationId": "NPWR00323_00",
        "trophyTitleName": "Battlefield: Bad Company",
        "trophyTitleIconUrl": "https://image.api.playstation.com/trophy/np/NPWR00323_00_00E856F909B1730BD388656CA12DD0CC936C7E7143/B0A60DEEFDA0C18DF759D7003F6169073073964D.PNG",
        "trophyTitlePlatform": "PS3",
        "definedTrophies": {
            "platinum": 1,
            "gold": 3,
            "silver": 5,
            "bronze": 42
        },
        "service": "trophy"
    },
    "NPWR00324_00": {
        "npCommunicationId": "NPWR00324_00",
        "trophyTitleName": "HEAVY RAIN™",
        "trophyTitleIconUrl": "https://image.api.playstation.com/trophy/np/NPWR00324_00_008DAB1F50430C4731BD0A51BAFE43A467A594392A/1E684EF7FDD6C36734E7B4ABDE1F2F8440DD1700.PNG",
        "trophyTitlePlatform": "PS3",
        "definedTrophies": {
            "platinum": 1,
            "gold": 2,
            "silver": 4,
            "bronze": 50
        },
        "service": "trophy"
    },
    "NPWR00328_00": {
        "npCommunicationId": "NPWR00328_00",
        "trophyTitleName": "Kane & Lynch 2: Dog Days",
        "trophyTitleIconUrl": "https://image.api.playstation.com/trophy/np/NPWR00328_00_0005BDA606B33F1CBFFA0FF22FCDC59AC9E95B48AA/48B5A1A95C08624FD16AEA4B278FDAE6FC0FC20B.PNG",
        "trophyTitlePlatform": "PS3",
        "definedTrophies": {
            "platinum": 1,
            "gold": 3,
            "silver": 7,
            "bronze": 50
        },
        "service": "trophy"
    },
    "NPWR00331_00": {
        "npCommunicationId": "NPWR00331_00",
        "trophyTitleName": "DRIVER San Francisco",
        "trophyTitleIconUrl": "https://image.api.playstation.com/trophy/np/NPWR00331_00_00894CA1AC36DA4DA9FCF3D9ECABE0BD54BE2D3B09/CF666EF2C89686B0E9586090CA3E6CC0B5DC5C47.PNG",
        "trophyTitlePlatform": "PS3",
        "definedTrophies": {
            "platinum": 1,
            "gold": 2,
            "silver": 10,
            "bronze": 38
        },
        "service": "trophy"
    },
    "NPWR00338_00": {
        "npCommunicationId": "NPWR00338_00",
        "trophyTitleName": "Virtua Tennis 2009",
        "trophyTitleIconUrl": "https://image.api.playstation.com/trophy/np/NPWR00338_00_00C1B47D33A0CBFF4E0B7C3FF52D5AAE6E20E7E3DC/529D4121EDA3D8CD1ADF2470E2E07B694D3926DC.PNG",
        "trophyTitlePlatform": "PS3",
        "definedTrophies": {
            "platinum": 1,
            "gold": 3,
            "silver": 5,
            "bronze": 42
        },
        "service": "trophy"
    },
    "NPWR00339_00": {
        "npCommunicationId": "NPWR00339_00",
        "trophyTitleName": "Mercenaries 2: World in Flames™",
        "trophyTitleIconUrl": "https://image.api.playstation.com/trophy/np/NPWR00339_00_00114C5E3E9443C8707207BCEACD591FE4957B3D6B/B5B81A9B958282567FAE6DEDA3DA5DC61FBA42AB.PNG",
        "trophyTitlePlatform": "PS3",
        "definedTrophies": {
            "platinum": 1,
            "gold": 4,
            "silver": 11,
            "bronze": 24
        },
        "service": "trophy"
    },
    "NPWR00345_00": {
        "npCommunicationId": "NPWR00345_00",
        "trophyTitleName": "GHOSTBUSTERS™: The Video Game",
        "trophyTitleIconUrl": "https://image.api.playstation.com/trophy/np/NPWR00345_00_00E06D1DCC4FCE51F2F177F5C197D7F8351601FD16/753F3509D24AC0F2EA816925CD8F1EB04D06D739.PNG",
        "trophyTitlePlatform": "PS3",
        "definedTrophies": {
            "platinum": 1,
            "gold": 4,
            "silver": 0,
            "bronze": 46
        },
        "service": "trophy"
    },
    "NPWR00346_00": {
        "npCommunicationId": "NPWR00346_00",
        "trophyTitleName": "Novastrike Trophies",
        "trophyTitleIconUrl": "https://image.api.playstation.com/trophy/np/NPWR00346_00_00ABF2D4395206862AC2156A4740F751530A2F4082/2675AD43A7E4B8DD4DF3D1308D9B0B523BF89AC9.PNG",
        "trophyTitlePlatform": "PS3",
        "definedTrophies": {
            "platinum": 0,
            "gold": 0,
            "silver": 4,
            "bronze": 12
        },
        "service": "trophy"
    },
    "NPWR00350_00": {
        "npCommunicationId": "NPWR00350_00",
        "trophyTitleName": "PixelJunk™ Eden / Encore",
        "trophyTitleIconUrl": "https://image.api.playstation.com/trophy/np/NPWR00350_00_003E7951836589EE9C1263078439CA7C0502044199/EDED87AC75C3379249C3C86EB475578D832F5942.PNG",
        "trophyTitlePlatform": "PS3",
        "definedTrophies": {
            "platinum": 0,
            "gold": 0,
            "silver": 2,
            "bronze": 30
        },
        "service": "trophy"
    },
    "NPWR00352_00": {
        "npCommunicationId": "NPWR00352_00",
        "trophyTitleName": "BioShock",
        "trophyTitleIconUrl": "https://image.api.playstation.com/trophy/np/NPWR00352_00_0054A97A00EA20990FC4F9D673CA9E90B5520B1D69/25E1901FBA6D18B9778DC3FFC260D664FF937D3F.PNG",
        "trophyTitlePlatform": "PS3",
        "definedTrophies": {
            "platinum": 1,
            "gold": 3,
            "silver": 3,
            "bronze": 59
        },
        "service": "trophy"
    },
    "NPWR00354_00": {
        "npCommunicationId": "NPWR00354_00",
        "trophyTitleName": "Worms™",
        "trophyTitleIconUrl": "https://image.api.playstation.com/trophy/np/NPWR00354_00_00DD430690ED5EA22EE1F39E030B5BF810D0A1623C/E594A18B240F7B7646E58DF3B175E424ABE04050.PNG",
        "trophyTitlePlatform": "PS3",
        "definedTrophies": {
            "platinum": 0,
            "gold": 1,
            "silver": 2,
            "bronze": 11
        },
        "service": "trophy"
    },
    "NPWR00355_00": {
        "npCommunicationId": "NPWR00355_00",
        "trophyTitleName": "Switchball®",
        "trophyTitleIconUrl": "https://image.api.playstation.com/trophy/np/NPWR00355_00_0056DEC60EF0F50F5D8727FE511F6DACC1E847D467/18265A31FF29BA473E1FAC6119D17FE933FB5FCB.PNG",
        "trophyTitlePlatform": "PS3",
        "definedTrophies": {
            "platinum": 0,
            "gold": 1,
            "silver": 4,
            "bronze": 7
        },
        "service": "trophy"
    },
    "NPWR00356_00": {
        "npCommunicationId": "NPWR00356_00",
        "trophyTitleName": "Mahjong Tales: Ancient Wisdom",
        "trophyTitleIconUrl": "https://image.api.playstation.com/trophy/np/NPWR00356_00_00F93425C7A6772D237AC6C209CA49D29861B44C27/C35721AA876EB875AE476A84DCC93D247F9E3BC5.PNG",
        "trophyTitlePlatform": "PS3",
        "definedTrophies": {
            "platinum": 0,
            "gold": 0,
            "silver": 5,
            "bronze": 16
        },
        "service": "trophy"
    },
    "NPWR00357_00": {
        "npCommunicationId": "NPWR00357_00",
        "trophyTitleName": "FIFA 09",
        "trophyTitleIconUrl": "https://image.api.playstation.com/trophy/np/NPWR00357_00_007DEB2E9EA9099AAC5F036FCBD2147F28DD8985F5/5182A4B3E04C5E469576AEE2BE059E0899C9E29D.PNG",
        "trophyTitlePlatform": "PS3",
        "definedTrophies": {
            "platinum": 1,
            "gold": 2,
            "silver": 17,
            "bronze": 37
        },
        "service": "trophy"
    },
    "NPWR00359_00": {
        "npCommunicationId": "NPWR00359_00",
        "trophyTitleName": "Quantum of Solace",
        "trophyTitleIconUrl": "https://image.api.playstation.com/trophy/np/NPWR00359_00_005CCB6C686C75A138A0EFDFA8E7E47BAB1A2E9242/2CCEF4677C11BDBF2517C6068EC1A3793A8CD438.PNG",
        "trophyTitlePlatform": "PS3",
        "definedTrophies": {
            "platinum": 1,
            "gold": 2,
            "silver": 8,
            "bronze": 40
        },
        "service": "trophy"
    },
    "NPWR00362_00": {
        "npCommunicationId": "NPWR00362_00",
        "trophyTitleName": "CRASH COMMANDO™",
        "trophyTitleIconUrl": "https://image.api.playstation.com/trophy/np/NPWR00362_00_00C7944FB4D00610124B5C7B0943DEA0F6F209DA49/5504715D732E1F03C633E5E6DC20B7BD75D77504.PNG",
        "trophyTitlePlatform": "PS3",
        "definedTrophies": {
            "platinum": 0,
            "gold": 1,
            "silver": 7,
            "bronze": 14
        },
        "service": "trophy"
    },
    "NPWR00373_00": {
        "npCommunicationId": "NPWR00373_00",
        "trophyTitleName": "THE KING OF FIGHTERS XII",
        "trophyTitleIconUrl": "https://image.api.playstation.com/trophy/np/NPWR00373_00_0028A1AEAE60144E27081A45B6E63FCCCF8A4CB5AA/A2FFC137B686E5709C59FFBCD8A03907A703FBCD.PNG",
        "trophyTitlePlatform": "PS3",
        "definedTrophies": {
            "platinum": 1,
            "gold": 3,
            "silver": 5,
            "bronze": 42
        },
        "service": "trophy"
    },
    "NPWR00374_00": {
        "npCommunicationId": "NPWR00374_00",
        "trophyTitleName": "Prince of Persia",
        "trophyTitleIconUrl": "https://image.api.playstation.com/trophy/np/NPWR00374_00_0062FDA111AD1057ADD0F9FB4CFF545B63A5B80BF6/5A9C195DE602A0FAD84D181146D3CB55D1D040D5.PNG",
        "trophyTitlePlatform": "PS3",
        "definedTrophies": {
            "platinum": 1,
            "gold": 3,
            "silver": 8,
            "bronze": 49
        },
        "service": "trophy"
    },
    "NPWR00375_00": {
        "npCommunicationId": "NPWR00375_00",
        "trophyTitleName": "Stormrise",
        "trophyTitleIconUrl": "https://image.api.playstation.com/trophy/np/NPWR00375_00_00E7EA7E3960BF8A9A7D9C92A9AA992D86003373AE/04176551C39CD165B2D7EE31D5411879CEAED216.PNG",
        "trophyTitlePlatform": "PS3",
        "definedTrophies": {
            "platinum": 1,
            "gold": 3,
            "silver": 7,
            "bronze": 33
        },
        "service": "trophy"
    },
    "NPWR00380_00": {
        "npCommunicationId": "NPWR00380_00",
        "trophyTitleName": "MAG™",
        "trophyTitleIconUrl": "https://image.api.playstation.com/trophy/np/NPWR00380_00_00BA0C5467ACEEF41E4A5B0748222BA6732DE84013/29719D0B82A87530E2E2BAE999CA770F80565153.PNG",
        "trophyTitlePlatform": "PS3",
        "definedTrophies": {
            "platinum": 1,
            "gold": 6,
            "silver": 15,
            "bronze": 22
        },
        "service": "trophy"
    },
    "NPWR00382_00": {
        "npCommunicationId": "NPWR00382_00",
        "trophyTitleName": "Burn Zombie Burn!",
        "trophyTitleIconUrl": "https://image.api.playstation.com/trophy/np/NPWR00382_00_0046BE0377292477D74004632DBE706C47C448FADC/E8BE3C9CF2C229F74BBA084F8FA0A000D2C0F7F5.PNG",
        "trophyTitlePlatform": "PS3",
        "definedTrophies": {
            "platinum": 0,
            "gold": 1,
            "silver": 5,
            "bronze": 17
        },
        "service": "trophy"
    },
    "NPWR00388_00": {
        "npCommunicationId": "NPWR00388_00",
        "trophyTitleName": "Rag Doll Kung Fu™: Fists of Plastic ",
        "trophyTitleIconUrl": "https://image.api.playstation.com/trophy/np/NPWR00388_00_004642E118DC37746B4F390599071BD9E0E94B5DEF/CAE0BAD73415EBD78631244996755FA77DD9ACB3.PNG",
        "trophyTitlePlatform": "PS3",
        "definedTrophies": {
            "platinum": 0,
            "gold": 1,
            "silver": 4,
            "bronze": 7
        },
        "service": "trophy"
    },
    "NPWR00389_00": {
        "npCommunicationId": "NPWR00389_00",
        "trophyTitleName": "Bomberman ULTRA",
        "trophyTitleIconUrl": "https://image.api.playstation.com/trophy/np/NPWR00389_00_00EF77F3D09A4948145205FD1771A9BD0F50B0E6DB/167CA29CE96DB9BA6F90BB4FE33C56D61FEBF1FE.PNG",
        "trophyTitlePlatform": "PS3",
        "definedTrophies": {
            "platinum": 0,
            "gold": 1,
            "silver": 4,
            "bronze": 6
        },
        "service": "trophy"
    },
    "NPWR00390_00": {
        "npCommunicationId": "NPWR00390_00",
        "trophyTitleName": "Shaun White Snowboarding",
        "trophyTitleIconUrl": "https://image.api.playstation.com/trophy/np/NPWR00390_00_00C90B56996D953C7777B44FA0B4296D4EC9AF5F5E/B350EA901BCE3D49E5C8586D09118C263D18CCCE.PNG",
        "trophyTitlePlatform": "PS3",
        "definedTrophies": {
            "platinum": 1,
            "gold": 3,
            "silver": 8,
            "bronze": 36
        },
        "service": "trophy"
    },
    "NPWR00391_00": {
        "npCommunicationId": "NPWR00391_00",
        "trophyTitleName": "Savage Moon™ Veteran's Awards",
        "trophyTitleIconUrl": "https://image.api.playstation.com/trophy/np/NPWR00391_00_000F1405DA09D704E15FDF633CF2142DB1EB707500/808DE29858BBE16B44E3D68886F7A9BF49A64F55.PNG",
        "trophyTitlePlatform": "PS3",
        "definedTrophies": {
            "platinum": 0,
            "gold": 2,
            "silver": 3,
            "bronze": 15
        },
        "service": "trophy"
    },
    "NPWR00394_00": {
        "npCommunicationId": "NPWR00394_00",
        "trophyTitleName": "LUMINES™ Supernova",
        "trophyTitleIconUrl": "https://image.api.playstation.com/trophy/np/NPWR00394_00_007C6C74CAA36BADE2EBFC0AED3A6A5B64FAC303B8/7457FAF0570113E43E7604216221B24CDE4165BA.PNG",
        "trophyTitlePlatform": "PS3",
        "definedTrophies": {
            "platinum": 0,
            "gold": 1,
            "silver": 4,
            "bronze": 6
        },
        "service": "trophy"
    },
    "NPWR00396_00": {
        "npCommunicationId": "NPWR00396_00",
        "trophyTitleName": "Magic Orbz",
        "trophyTitleIconUrl": "https://image.api.playstation.com/trophy/np/NPWR00396_00_0095F8B23A614309C97407D2C83839325E0FC3380E/F2841A6381F304657548B800F175E0C78F8DAA34.PNG",
        "trophyTitlePlatform": "PS3",
        "definedTrophies": {
            "platinum": 0,
            "gold": 1,
            "silver": 10,
            "bronze": 15
        },
        "service": "trophy"
    },
    "NPWR00398_00": {
        "npCommunicationId": "NPWR00398_00",
        "trophyTitleName": "Brain Challenge",
        "trophyTitleIconUrl": "https://image.api.playstation.com/trophy/np/NPWR00398_00_003936AB184362A6A9128BAEBD454898AFFC2F0103/C63CF8D2B040200F3AD2A0C5BC06516181169983.PNG",
        "trophyTitlePlatform": "PS3",
        "definedTrophies": {
            "platinum": 0,
            "gold": 1,
            "silver": 4,
            "bronze": 7
        },
        "service": "trophy"
    },
    "NPWR00399_00": {
        "npCommunicationId": "NPWR00399_00",
        "trophyTitleName": "AQUANAUT'S HOLIDAY ™　- Hidden memories -",
        "trophyTitleIconUrl": "https://image.api.playstation.com/trophy/np/NPWR00399_00_007E353F7C2BBB8015B96777A28D1C8D5B883B828F/A78B08488B7D8FAE73D5C36FA1A41C9AB2562B88.PNG",
        "trophyTitlePlatform": "PS3",
        "definedTrophies": {
            "platinum": 1,
            "gold": 2,
            "silver": 8,
            "bronze": 39
        },
        "service": "trophy"
    },
    "NPWR00400_00": {
        "npCommunicationId": "NPWR00400_00",
        "trophyTitleName": "魔界戦記ディスガイア３ ",
        "trophyTitleIconUrl": "https://image.api.playstation.com/trophy/np/NPWR00400_00_0099B656033E0CDEF95BFDFDF840A21EC507769613/450585D32A39AA7F78747BFC0B92347D6D9C9442.PNG",
        "trophyTitlePlatform": "PS3",
        "definedTrophies": {
            "platinum": 1,
            "gold": 3,
            "silver": 5,
            "bronze": 42
        },
        "service": "trophy"
    },
    "NPWR00403_00": {
        "npCommunicationId": "NPWR00403_00",
        "trophyTitleName": "Astro Tripper",
        "trophyTitleIconUrl": "https://image.api.playstation.com/trophy/np/NPWR00403_00_003ACD0A1292148CEA4A080D942AAD908188DF359C/6A31CB8D3FF48ACA1B4273FCB742DD5E6B99E3EC.PNG",
        "trophyTitlePlatform": "PS3",
        "definedTrophies": {
            "platinum": 0,
            "gold": 2,
            "silver": 3,
            "bronze": 3
        },
        "service": "trophy"
    },
    "NPWR00404_00": {
        "npCommunicationId": "NPWR00404_00",
        "trophyTitleName": "RESIDENT EVIL 5",
        "trophyTitleIconUrl": "https://image.api.playstation.com/trophy/np/NPWR00404_00_00BF56688E8386CFCFBAF030517D8FFDD6FE43429B/59EA12A11A1F71D0B81E849720588D149D210EB7.PNG",
        "trophyTitlePlatform": "PS3",
        "definedTrophies": {
            "platinum": 1,
            "gold": 1,
            "silver": 16,
            "bronze": 53
        },
        "service": "trophy"
    },
    "NPWR00406_00": {
        "npCommunicationId": "NPWR00406_00",
        "trophyTitleName": "Supersonic Acrobatic Rocket-Powered Battle-Cars",
        "trophyTitleIconUrl": "https://image.api.playstation.com/trophy/np/NPWR00406_00_0073BD39F0AA954F0F890C0FAA6A7664BAD3E46DA2/52909F135D7A33B141002F5D17D78343074E2B51.PNG",
        "trophyTitlePlatform": "PS3",
        "definedTrophies": {
            "platinum": 0,
            "gold": 1,
            "silver": 2,
            "bronze": 11
        },
        "service": "trophy"
    },
    "NPWR00408_00": {
        "npCommunicationId": "NPWR00408_00",
        "trophyTitleName": "ZEN Pinball",
        "trophyTitleIconUrl": "https://image.api.playstation.com/trophy/np/NPWR00408_00_000A6746A47DB3B95D3CEF9C9841502BECE2D3EC67/7B7F9FCFED841E65C066E5E4DBA23195D70F6EFC.PNG",
        "trophyTitlePlatform": "PS3",
        "definedTrophies": {
            "platinum": 0,
            "gold": 0,
            "silver": 13,
            "bronze": 35
        },
        "service": "trophy"
    },
    "NPWR00409_00": {
        "npCommunicationId": "NPWR00409_00",
        "trophyTitleName": "SPELUNKER HD",
        "trophyTitleIconUrl": "https://image.api.playstation.com/trophy/np/NPWR00409_00_0022B8D1E550520323C4D4D376B1838C277ABCEF19/FA00C21A4007B0434E4BA0E0E35C52D1E85267F4.PNG",
        "trophyTitlePlatform": "PS3",
        "definedTrophies": {
            "platinum": 1,
            "gold": 12,
            "silver": 27,
            "bronze": 34
        },
        "service": "trophy"
    },
    "NPWR00410_00": {
        "npCommunicationId": "NPWR00410_00",
        "trophyTitleName": "Buzz!™: Quiz TV",
        "trophyTitleIconUrl": "https://image.api.playstation.com/trophy/np/NPWR00410_00_006143EE503CDACF3B747425E7C24EB0F202BF7421/335DED060C5D2816EF2C52D7683E5F2C925C0D3E.PNG",
        "trophyTitlePlatform": "PS3",
        "definedTrophies": {
            "platinum": 1,
            "gold": 7,
            "silver": 11,
            "bronze": 6
        },
        "service": "trophy"
    },
    "NPWR00413_00": {
        "npCommunicationId": "NPWR00413_00",
        "trophyTitleName": "Linger In Shadows™",
        "trophyTitleIconUrl": "https://image.api.playstation.com/trophy/np/NPWR00413_00_00589B053CC7E76ED50365094B182843A16C7228DE/BDFE923D25A30B5308EE5A3CB12C5793EC1E7492.PNG",
        "trophyTitlePlatform": "PS3",
        "definedTrophies": {
            "platinum": 0,
            "gold": 0,
            "silver": 5,
            "bronze": 11
        },
        "service": "trophy"
    },
    "NPWR00414_00": {
        "npCommunicationId": "NPWR00414_00",
        "trophyTitleName": "Diner Dash®",
        "trophyTitleIconUrl": "https://image.api.playstation.com/trophy/np/NPWR00414_00_00D9C60AFBF5F6D7C881583BB5E5565EAB16408BE0/CDA999B6315E43FE591364F0A4CE3F69AC5A1526.PNG",
        "trophyTitlePlatform": "PS3",
        "definedTrophies": {
            "platinum": 0,
            "gold": 1,
            "silver": 3,
            "bronze": 8
        },
        "service": "trophy"
    },
    "NPWR00416_00": {
        "npCommunicationId": "NPWR00416_00",
        "trophyTitleName": "Disgaea 3",
        "trophyTitleIconUrl": "https://image.api.playstation.com/trophy/np/NPWR00416_00_00EFFE9CF0E237EF4CB9285299AD2BF5FF43BD4BFF/54C52113131E12B922F5E0DB451F79E332BC2D12.PNG",
        "trophyTitlePlatform": "PS3",
        "definedTrophies": {
            "platinum": 1,
            "gold": 3,
            "silver": 5,
            "bronze": 42
        },
        "service": "trophy"
    },
    "NPWR00419_00": {
        "npCommunicationId": "NPWR00419_00",
        "trophyTitleName": "Far Cry® 2",
        "trophyTitleIconUrl": "https://image.api.playstation.com/trophy/np/NPWR00419_00_00F2B21587617532C805C92AE0CFD94AB3B12F548E/6233B963985CD6E85653A1E160E073C6688BE263.PNG",
        "trophyTitlePlatform": "PS3",
        "definedTrophies": {
            "platinum": 1,
            "gold": 3,
            "silver": 7,
            "bronze": 38
        },
        "service": "trophy"
    },
    "NPWR00421_00": {
        "npCommunicationId": "NPWR00421_00",
        "trophyTitleName": "TV Show King Trophy Set",
        "trophyTitleIconUrl": "https://image.api.playstation.com/trophy/np/NPWR00421_00_00B7E9B89CBB71FF93F87CF878D0C153830001DC9D/CD5ADD87D912B6200879C81ACD1B42A2F437550C.PNG",
        "trophyTitlePlatform": "PS3",
        "definedTrophies": {
            "platinum": 0,
            "gold": 0,
            "silver": 2,
            "bronze": 17
        },
        "service": "trophy"
    },
    "NPWR00425_00": {
        "npCommunicationId": "NPWR00425_00",
        "trophyTitleName": "Assault Heroes ™",
        "trophyTitleIconUrl": "https://image.api.playstation.com/trophy/np/NPWR00425_00_009B135921B9C28484D95A54EAAFE46FC85E84332D/78C3E138DF0FAF6675A4F6CB081512AAE8ED6B02.PNG",
        "trophyTitlePlatform": "PS3",
        "definedTrophies": {
            "platinum": 0,
            "gold": 1,
            "silver": 4,
            "bronze": 7
        },
        "service": "trophy"
    },
    "NPWR00426_00": {
        "npCommunicationId": "NPWR00426_00",
        "trophyTitleName": "Sonic & SEGA All-Stars Racing",
        "trophyTitleIconUrl": "https://image.api.playstation.com/trophy/np/NPWR00426_00_00D722DB194AE6DCF85D354142E295D6FC2962B37A/91F0600A078C9B6BBF0EF750D27AE2087C37BC83.PNG",
        "trophyTitlePlatform": "PS3",
        "definedTrophies": {
            "platinum": 1,
            "gold": 1,
            "silver": 13,
            "bronze": 35
        },
        "service": "trophy"
    },
    "NPWR00429_00": {
        "npCommunicationId": "NPWR00429_00",
        "trophyTitleName": "DiRT 2",
        "trophyTitleIconUrl": "https://image.api.playstation.com/trophy/np/NPWR00429_00_00EF5F053C7DF17A0B14E6DB6E2A4E65B5516EDA41/D91A867E0A4EDE86E5722072185299C5A0ED3FC5.PNG",
        "trophyTitlePlatform": "PS3",
        "definedTrophies": {
            "platinum": 1,
            "gold": 3,
            "silver": 8,
            "bronze": 36
        },
        "service": "trophy"
    },
    "NPWR00430_00": {
        "npCommunicationId": "NPWR00430_00",
        "trophyTitleName": "Skate 2",
        "trophyTitleIconUrl": "https://image.api.playstation.com/trophy/np/NPWR00430_00_0027D4819936ACC26CA6B815890FED4D03B10C7A3A/15A03260D37F9890FCFD942DA155FDF811F4FCE1.PNG",
        "trophyTitlePlatform": "PS3",
        "definedTrophies": {
            "platinum": 1,
            "gold": 2,
            "silver": 9,
            "bronze": 35
        },
        "service": "trophy"
    },
    "NPWR00432_00": {
        "npCommunicationId": "NPWR00432_00",
        "trophyTitleName": "PlayStation®Home",
        "trophyTitleIconUrl": "https://image.api.playstation.com/trophy/np/NPWR00432_00_0003472C02B2710AD5532F20F4D34C426E6A488314/E2E54879114441EAF2E889CD1F5CC77E443D1AB8.PNG",
        "trophyTitlePlatform": "PS3",
        "definedTrophies": {
            "platinum": 0,
            "gold": 1,
            "silver": 3,
            "bronze": 9
        },
        "service": "trophy"
    },
    "NPWR00434_00": {
        "npCommunicationId": "NPWR00434_00",
        "trophyTitleName": "STREET FIGHTER Ⅳ Trophy pack.",
        "trophyTitleIconUrl": "https://image.api.playstation.com/trophy/np/NPWR00434_00_003BC625ACCD0C2A5C5B4960CA1C23C77EC443B477/D3154DF2AA814CA3F240222F084F18AFE8D3D8F1.PNG",
        "trophyTitlePlatform": "PS3",
        "definedTrophies": {
            "platinum": 1,
            "gold": 2,
            "silver": 10,
            "bronze": 35
        },
        "service": "trophy"
    },
    "NPWR00439_00": {
        "npCommunicationId": "NPWR00439_00",
        "trophyTitleName": "UFC 2009 Undisputed",
        "trophyTitleIconUrl": "https://image.api.playstation.com/trophy/np/NPWR00439_00_00E5CECBEF7EC8E4BAD8EBF5EE966A264AEBA49367/1F93E4C76E65C71461D30612F87CAFF6BA3F6B50.PNG",
        "trophyTitlePlatform": "PS3",
        "definedTrophies": {
            "platinum": 1,
            "gold": 4,
            "silver": 16,
            "bronze": 10
        },
        "service": "trophy"
    },
    "NPWR00440_00": {
        "npCommunicationId": "NPWR00440_00",
        "trophyTitleName": "Rock Band 2",
        "trophyTitleIconUrl": "https://image.api.playstation.com/trophy/np/NPWR00440_00_00C3B2C594F025643D79805AFDB7BA7E81F31B0859/F35F2AE40938B9F92908432B8DDEBCE2CFCDC161.PNG",
        "trophyTitlePlatform": "PS3",
        "definedTrophies": {
            "platinum": 1,
            "gold": 2,
            "silver": 10,
            "bronze": 38
        },
        "service": "trophy"
    },
    "NPWR00441_00": {
        "npCommunicationId": "NPWR00441_00",
        "trophyTitleName": "Tom Clancy's EndWar™",
        "trophyTitleIconUrl": "https://image.api.playstation.com/trophy/np/NPWR00441_00_00F8D91CE108924BCEA40FB8363E3702A8259DFD2D/DBB3D1657F2E65634A2C481616B7644B2CAFFBE6.PNG",
        "trophyTitlePlatform": "PS3",
        "definedTrophies": {
            "platinum": 1,
            "gold": 2,
            "silver": 11,
            "bronze": 49
        },
        "service": "trophy"
    },
    "NPWR00442_00": {
        "npCommunicationId": "NPWR00442_00",
        "trophyTitleName": "Transformers™: Revenge of The Fallen™",
        "trophyTitleIconUrl": "https://image.api.playstation.com/trophy/np/NPWR00442_00_0071A66F70EE64B2877379662C64573A89A0376E0D/326654840C1C3429AA3C313C1441C79E9ED9F4D9.PNG",
        "trophyTitlePlatform": "PS3",
        "definedTrophies": {
            "platinum": 1,
            "gold": 5,
            "silver": 7,
            "bronze": 39
        },
        "service": "trophy"
    },
    "NPWR00447_00": {
        "npCommunicationId": "NPWR00447_00",
        "trophyTitleName": "Sacred 2 - Fallen Angel\n",
        "trophyTitleIconUrl": "https://image.api.playstation.com/trophy/np/NPWR00447_00_009D8DA892DEEBA752E505C0C86D559DF91B928D69/58DC098D0B1E2E260887257FFBEF746C74D11E2A.PNG",
        "trophyTitlePlatform": "PS3",
        "definedTrophies": {
            "platinum": 1,
            "gold": 2,
            "silver": 12,
            "bronze": 34
        },
        "service": "trophy"
    },
    "NPWR00449_00": {
        "npCommunicationId": "NPWR00449_00",
        "trophyTitleName": "Uncharted: Drake's Fortune™",
        "trophyTitleIconUrl": "https://image.api.playstation.com/trophy/np/NPWR00449_00_00727FDB8B71A3D03045ABCC7984807B8991254509/7CFF4AF57E944459DA3F079205E96BE52ECCA663.PNG",
        "trophyTitlePlatform": "PS3",
        "definedTrophies": {
            "platinum": 1,
            "gold": 3,
            "silver": 8,
            "bronze": 36
        },
        "service": "trophy"
    },
    "NPWR00450_00": {
        "npCommunicationId": "NPWR00450_00",
        "trophyTitleName": "Blitz: The League II",
        "trophyTitleIconUrl": "https://image.api.playstation.com/trophy/np/NPWR00450_00_00125FBD79E523E019F4A8A3B915559871EC4AC6C1/326BAD56708205654BA8556E4797F5932A464340.PNG",
        "trophyTitlePlatform": "PS3",
        "definedTrophies": {
            "platinum": 1,
            "gold": 2,
            "silver": 11,
            "bronze": 36
        },
        "service": "trophy"
    },
    "NPWR00455_00": {
        "npCommunicationId": "NPWR00455_00",
        "trophyTitleName": "Wolfenstein™",
        "trophyTitleIconUrl": "https://image.api.playstation.com/trophy/np/NPWR00455_00_00C1DE0263EC487D0D5F38F3481B29C8138FC49D01/7C039C10EE7CF59E534E6FFC4B073694E6642471.PNG",
        "trophyTitlePlatform": "PS3",
        "definedTrophies": {
            "platinum": 1,
            "gold": 1,
            "silver": 15,
            "bronze": 33
        },
        "service": "trophy"
    },
    "NPWR00456_00": {
        "npCommunicationId": "NPWR00456_00",
        "trophyTitleName": "Days Of Thunder NASCAR",
        "trophyTitleIconUrl": "https://image.api.playstation.com/trophy/np/NPWR00456_00_00E3CACF470EC4856C3AA270CE337B4591BD6F6D84/D5784B1D6F1293661AAE98F017DD799BE5F8FC24.PNG",
        "trophyTitlePlatform": "PS3",
        "definedTrophies": {
            "platinum": 0,
            "gold": 1,
            "silver": 0,
            "bronze": 15
        },
        "service": "trophy"
    },
    "NPWR00458_00": {
        "npCommunicationId": "NPWR00458_00",
        "trophyTitleName": "OutRun™ Online Arcade",
        "trophyTitleIconUrl": "https://image.api.playstation.com/trophy/np/NPWR00458_00_00B55F1714FD996FB02164A4BEC3224DCADB0C5C0F/A48DB08C04FCDFD5843D0AC0BBCC1ABA387E8BC0.PNG",
        "trophyTitlePlatform": "PS3",
        "definedTrophies": {
            "platinum": 0,
            "gold": 1,
            "silver": 4,
            "bronze": 7
        },
        "service": "trophy"
    },
    "NPWR00459_00": {
        "npCommunicationId": "NPWR00459_00",
        "trophyTitleName": "Kung Fu Rider™ Trophy Set",
        "trophyTitleIconUrl": "https://image.api.playstation.com/trophy/np/NPWR00459_00_008BFC848E610084A7AD1AC359E2FBAE4F26647489/EE86645FE393C00FA40D31248F18FC0B06AA0D13.PNG",
        "trophyTitlePlatform": "PS3",
        "definedTrophies": {
            "platinum": 0,
            "gold": 1,
            "silver": 3,
            "bronze": 9
        },
        "service": "trophy"
    },
    "NPWR00461_00": {
        "npCommunicationId": "NPWR00461_00",
        "trophyTitleName": "Aliens vs Predator",
        "trophyTitleIconUrl": "https://image.api.playstation.com/trophy/np/NPWR00461_00_005330DB3C1E9096B8BBA2A6B22025B1E209AD87CA/DFD7F21557DCB9843994628DA4F4570B336137D5.PNG",
        "trophyTitlePlatform": "PS3",
        "definedTrophies": {
            "platinum": 1,
            "gold": 1,
            "silver": 13,
            "bronze": 35
        },
        "service": "trophy"
    },
    "NPWR00462_00": {
        "npCommunicationId": "NPWR00462_00",
        "trophyTitleName": "Uncharted 2: Among Thieves™ ",
        "trophyTitleIconUrl": "https://image.api.playstation.com/trophy/np/NPWR00462_00_00534AD6647D743E1E7466BB16667F7E6334D643DD/4226B4020FFEBD3538E0A4FB2BB8375E4BD4643B.PNG",
        "trophyTitlePlatform": "PS3",
        "definedTrophies": {
            "platinum": 1,
            "gold": 3,
            "silver": 10,
            "bronze": 57
        },
        "service": "trophy"
    },
    "NPWR00464_00": {
        "npCommunicationId": "NPWR00464_00",
        "trophyTitleName": "Dead Space™",
        "trophyTitleIconUrl": "https://image.api.playstation.com/trophy/np/NPWR00464_00_00DBE20A1AFA75AF0CD243472031097C1757596370/F224070B5514CF1DBFDBE87CC7BD46038EA94C3A.PNG",
        "trophyTitlePlatform": "PS3",
        "definedTrophies": {
            "platinum": 1,
            "gold": 3,
            "silver": 4,
            "bronze": 41
        },
        "service": "trophy"
    },
    "NPWR00466_00": {
        "npCommunicationId": "NPWR00466_00",
        "trophyTitleName": "Wheelman",
        "trophyTitleIconUrl": "https://image.api.playstation.com/trophy/np/NPWR00466_00_00436D4852A154649E99C88FDB828AF6A1ADA152D0/CECAD343098DF569E1A672519231AB52CA8B13CF.PNG",
        "trophyTitlePlatform": "PS3",
        "definedTrophies": {
            "platinum": 1,
            "gold": 3,
            "silver": 12,
            "bronze": 28
        },
        "service": "trophy"
    },
    "NPWR00467_00": {
        "npCommunicationId": "NPWR00467_00",
        "trophyTitleName": "Call of Duty®: World at War",
        "trophyTitleIconUrl": "https://image.api.playstation.com/trophy/np/NPWR00467_00_0051F43B35E40640DD8D6C4EFA1DBB0F467108D027/7C77C453CAA0B582F9D70DD16B5EE6DC7515441D.PNG",
        "trophyTitlePlatform": "PS3",
        "definedTrophies": {
            "platinum": 1,
            "gold": 2,
            "silver": 18,
            "bronze": 44
        },
        "service": "trophy"
    },
    "NPWR00468_00": {
        "npCommunicationId": "NPWR00468_00",
        "trophyTitleName": "F.E.A.R. 2: Project Origin",
        "trophyTitleIconUrl": "https://image.api.playstation.com/trophy/np/NPWR00468_00_00A9BD9BFED5AEFCA7977B9D8CC016E2449DE419C5/530D88F3B94DCE1300DB2DB0FE1A472E3D49D8FD.PNG",
        "trophyTitlePlatform": "PS3",
        "definedTrophies": {
            "platinum": 1,
            "gold": 2,
            "silver": 7,
            "bronze": 49
        },
        "service": "trophy"
    },
    "NPWR00469_00": {
        "npCommunicationId": "NPWR00469_00",
        "trophyTitleName": "Critter Crunch",
        "trophyTitleIconUrl": "https://image.api.playstation.com/trophy/np/NPWR00469_00_007CBE63F073F357DC6F235A7961CF88804BC51476/951A26F95BB71BA2073C854E3F2E10D4D855F619.PNG",
        "trophyTitlePlatform": "PS3",
        "definedTrophies": {
            "platinum": 0,
            "gold": 1,
            "silver": 2,
            "bronze": 11
        },
        "service": "trophy"
    },
    "NPWR00471_00": {
        "npCommunicationId": "NPWR00471_00",
        "trophyTitleName": "NBA 09 The Inside",
        "trophyTitleIconUrl": "https://image.api.playstation.com/trophy/np/NPWR00471_00_00892B71BEF736F6B594E46446A41B0FD3509832BE/A312B2DE61544FB4FF2B78790B24566C5A5A0B11.PNG",
        "trophyTitlePlatform": "PS3",
        "definedTrophies": {
            "platinum": 1,
            "gold": 6,
            "silver": 8,
            "bronze": 13
        },
        "service": "trophy"
    },
    "NPWR00472_00": {
        "npCommunicationId": "NPWR00472_00",
        "trophyTitleName": "Ride to Hell: Retribution",
        "trophyTitleIconUrl": "https://image.api.playstation.com/trophy/np/NPWR00472_00_0092D6F029453D9C4912F788D36D54C07262C2D5F8/4CD29FCFDB3DA24D92607A4F6E13E936B558C811.PNG",
        "trophyTitlePlatform": "PS3",
        "definedTrophies": {
            "platinum": 1,
            "gold": 3,
            "silver": 20,
            "bronze": 24
        },
        "service": "trophy"
    },
    "NPWR00473_00": {
        "npCommunicationId": "NPWR00473_00",
        "trophyTitleName": "3D Ultra MiniGolf Adventures 2",
        "trophyTitleIconUrl": "https://image.api.playstation.com/trophy/np/NPWR00473_00_0040634B9ED6647B196AB585D634CE62D30C7DC930/9E8F4B556B029022FFC69B1B2E845F495A14610E.PNG",
        "trophyTitlePlatform": "PS3",
        "definedTrophies": {
            "platinum": 0,
            "gold": 1,
            "silver": 4,
            "bronze": 7
        },
        "service": "trophy"
    },
    "NPWR00476_00": {
        "npCommunicationId": "NPWR00476_00",
        "trophyTitleName": "NAMCO MUSEUM ESSENTIALS™",
        "trophyTitleIconUrl": "https://image.api.playstation.com/trophy/np/NPWR00476_00_00699B7C8B6D51B3D8FD1BAC5D7602986A00A75C99/FB631E983472F248ADEA3E2677CE1BF54D735692.PNG",
        "trophyTitlePlatform": "PS3",
        "definedTrophies": {
            "platinum": 0,
            "gold": 1,
            "silver": 5,
            "bronze": 5
        },
        "service": "trophy"
    },
    "NPWR00478_00": {
        "npCommunicationId": "NPWR00478_00",
        "trophyTitleName": "Guitar Hero Metallica",
        "trophyTitleIconUrl": "https://image.api.playstation.com/trophy/np/NPWR00478_00_0076CC4B88BBF60907CB3EF79BCCF467CEC589AE59/85CFD3FF1244A3CB17412D9BD04E015633FFBEE3.PNG",
        "trophyTitlePlatform": "PS3",
        "definedTrophies": {
            "platinum": 1,
            "gold": 1,
            "silver": 12,
            "bronze": 37
        },
        "service": "trophy"
    },
    "NPWR00479_00": {
        "npCommunicationId": "NPWR00479_00",
        "trophyTitleName": "Comet Crash",
        "trophyTitleIconUrl": "https://image.api.playstation.com/trophy/np/NPWR00479_00_000399F648198039F678DA753CF4AA04048C9691C5/C5A8D8208D3C87F3B143C91136CF6D7DA8641B7B.PNG",
        "trophyTitlePlatform": "PS3",
        "definedTrophies": {
            "platinum": 0,
            "gold": 1,
            "silver": 6,
            "bronze": 16
        },
        "service": "trophy"
    },
    "NPWR00481_00": {
        "npCommunicationId": "NPWR00481_00",
        "trophyTitleName": "FUEL™",
        "trophyTitleIconUrl": "https://image.api.playstation.com/trophy/np/NPWR00481_00_00E03BD10958887B54ADD36CD4DA51B81B1EE4BEE2/FEDAAF08BF0983D2CF4D22104819E02E5C3A4C12.PNG",
        "trophyTitlePlatform": "PS3",
        "definedTrophies": {
            "platinum": 1,
            "gold": 2,
            "silver": 9,
            "bronze": 34
        },
        "service": "trophy"
    },
    "NPWR00482_00": {
        "npCommunicationId": "NPWR00482_00",
        "trophyTitleName": "TEKKEN 6 Trophy Set",
        "trophyTitleIconUrl": "https://image.api.playstation.com/trophy/np/NPWR00482_00_004DB8386A0180C345E258822BAB3DAD9B59F92C31/BE617A079A95B99280BECBD08A685763F60216D0.PNG",
        "trophyTitlePlatform": "PS3",
        "definedTrophies": {
            "platinum": 1,
            "gold": 2,
            "silver": 11,
            "bronze": 36
        },
        "service": "trophy"
    },
    "NPWR00483_00": {
        "npCommunicationId": "NPWR00483_00",
        "trophyTitleName": "Monsters vs. Aliens (TM)",
        "trophyTitleIconUrl": "https://image.api.playstation.com/trophy/np/NPWR00483_00_00F12BE25967E88BDDB547085F874CD0921EE92E28/8BC5B411F7F187F284730BE15DD5CFA48CAAC567.PNG",
        "trophyTitlePlatform": "PS3",
        "definedTrophies": {
            "platinum": 1,
            "gold": 4,
            "silver": 5,
            "bronze": 36
        },
        "service": "trophy"
    },
    "NPWR00484_00": {
        "npCommunicationId": "NPWR00484_00",
        "trophyTitleName": "Aliens: Colonial Marines",
        "trophyTitleIconUrl": "https://image.api.playstation.com/trophy/np/NPWR00484_00_0070608D659334E74EE8DEDEF234814F29F8196F2E/0CA5C0076FBB2EBDDF73A6095EC99254DF1CAF44.PNG",
        "trophyTitlePlatform": "PS3",
        "definedTrophies": {
            "platinum": 1,
            "gold": 2,
            "silver": 13,
            "bronze": 45
        },
        "service": "trophy"
    },
    "NPWR00485_00": {
        "npCommunicationId": "NPWR00485_00",
        "trophyTitleName": "Buzz!™: Brain of...",
        "trophyTitleIconUrl": "https://image.api.playstation.com/trophy/np/NPWR00485_00_00C6B09AB09849A29B363058712E93BCD9B3D246E0/CD63C1D62EF4829558CDF14E3FEA265F26070463.PNG",
        "trophyTitlePlatform": "PS3",
        "definedTrophies": {
            "platinum": 1,
            "gold": 7,
            "silver": 11,
            "bronze": 6
        },
        "service": "trophy"
    },
    "NPWR00489_00": {
        "npCommunicationId": "NPWR00489_00",
        "trophyTitleName": "Penny Arcade Adventures: On the Rain-Slick Precipice of Darkness, Episode One",
        "trophyTitleIconUrl": "https://image.api.playstation.com/trophy/np/NPWR00489_00_00521F525ACE4CAE24F2C2D41B9E055B146C0E10F3/2B1CCEC723FB4278B295415139624BC348F48AB9.PNG",
        "trophyTitlePlatform": "PS3",
        "definedTrophies": {
            "platinum": 0,
            "gold": 1,
            "silver": 4,
            "bronze": 7
        },
        "service": "trophy"
    },
    "NPWR00491_00": {
        "npCommunicationId": "NPWR00491_00",
        "trophyTitleName": "Cuboid",
        "trophyTitleIconUrl": "https://image.api.playstation.com/trophy/np/NPWR00491_00_00E3B46DA6CD9AE9D8F03C90B70A9BDC9DBDB60031/38432D900DE1C0C41D7A7CA537567F538B419078.PNG",
        "trophyTitlePlatform": "PS3",
        "definedTrophies": {
            "platinum": 0,
            "gold": 0,
            "silver": 6,
            "bronze": 18
        },
        "service": "trophy"
    }
}